[{"id":1,"service":1,"approach":"<p><span style=\"font-family: &quot;Segoe UI&quot;; font-size: 24px;\">For employees to contribute optimally, organizations need to engage the whole person\u2019s;<\/span><\/p><p><span style=\"font-family: &quot;Segoe UI&quot;; font-size: 24px;\">Hand, Head, and Heart<br><\/span><br><\/p>","approach_ar":"<p><span style=\"font-family: &quot;Segoe UI&quot;; font-size: 24px;\">\u0644\u0643\u064a \u064a\u0633\u0627\u0647\u0645 \u0627\u0644\u0645\u0648\u0638\u0641\u0648\u0646 \u0628\u0634\u0643\u0644 \u0645\u062b\u0627\u0644\u064a\u060c \u062a\u062d\u062a\u0627\u062c \u0627\u0644\u0645\u0646\u0638\u0645\u0627\u062a \u0625\u0644\u0649 \u0625\u0634\u0631\u0627\u0643 \u0627\u0644\u0634\u062e\u0635 \u0628\u0623\u0643\u0645\u0644\u0647\u061b<\/span><\/p><p><span style=\"font-family: Cairo, sans-serif; font-size: 24px;\"><span style=\"font-family: &quot;Segoe UI&quot;;\">\u0627\u0644\u064a\u062f \u0648\u0627\u0644\u0639\u0642\u0644 \u0648\u0627\u0644\u0642\u0644\u0628<\/span><br><\/span><br><\/p>","icon":"20240623175222-3h-3.png","is_active":0,"deleted_at":null,"created_at":"2024-06-23 17:52:22","updated_at":"2024-06-23 17:52:22"},{"id":2,"service":2,"approach":"<p><span style=\"font-family: Cairo, sans-serif; font-size: 14.4px; text-align: center;\">We believe that HR value is defined by the receivers(managers) and not by the giver (HR department) and thus we assess the managers' experience in handling HR activities in a way serving their business needs.<\/span><br><\/p>","approach_ar":"<p><span style=\"font-family: Cairo, sans-serif; font-size: 14.4px; text-align: center;\">\u0646\u0624\u0645\u0646 \u0628\u0623\u0646 \u0645\u0646 \u064a\u062d\u062f\u062f \u0627\u0644\u0642\u064a\u0645\u0629 \u0627\u0644\u062d\u0642\u064a\u0642\u064a\u0629 \u0644\u0642\u0633\u0645 \u0627\u0644\u0645\u0648\u0627\u0631\u062f \u0627\u0644\u0628\u0634\u0631\u064a\u0629 \u0647\u0645 \u0627\u0644\u0645\u062f\u064a\u0631\u064a\u0646 \u060c \u0648\u0644\u0647\u0630\u0627 \u064a\u0639\u062a\u0645\u062f \u0627\u0644\u0645\u0646\u0647\u062c \u0639\u0644\u0649 \u062a\u0642\u064a\u064a\u0645 \u062a\u062c\u0631\u0628\u0629 \u0627\u0644\u0645\u062f\u064a\u0631\u064a\u0646 \u0644\u0623\u0646\u0634\u0637\u0629 \u0627\u0644\u0645\u0648\u0627\u0631\u062f \u0627\u0644\u0628\u0634\u0631\u064a\u0629 \u0628\u0645\u0627 \u064a\u062e\u062f\u0645 \u0627\u0644\u0623\u0647\u062f\u0627\u0641 \u0627\u0644\u0625\u0633\u062a\u0631\u0627\u062a\u064a\u062c\u064a\u0629<\/span><br><\/p>","icon":"20240625100038-HR Diagnostic Approach icon 1.png","is_active":0,"deleted_at":null,"created_at":"2024-06-25 10:00:38","updated_at":"2024-06-25 10:00:38"},{"id":3,"service":3,"approach":"<p class=\"MsoNormal\"><span style=\"font-size: 9pt; line-height: 107%; font-family: &quot;Segoe UI&quot;, sans-serif; color: rgb(32, 56, 100); background-image: initial; background-position: initial; background-size: initial; background-repeat: initial; background-attachment: initial; background-origin: initial; background-clip: initial;\">It is an\r\neasy-to-administer questionnaire for reviewing leaders at any level of\r\nmanagement. It captures confidential feedback from the individual manager,\r\nhis\/her own manager, peers, and direct reports. The report provides a measure\r\nof the individual\u2019s attitude, behavior, and performance.<\/span><span style=\"font-size:9.0pt;line-height:107%\"><o:p><\/o:p><\/span><\/p>","approach_ar":"<p class=\"MsoNormal\"><span style=\"font-size: 9pt; line-height: 107%; font-family: &quot;Segoe UI&quot;, sans-serif; color: rgb(32, 56, 100); background-image: initial; background-position: initial; background-size: initial; background-repeat: initial; background-attachment: initial; background-origin: initial; background-clip: initial;\">\u0625\u0646\u0647 \u0627\u0633\u062a\u0628\u064a\u0627\u0646 \u0633\u0647\u0644 \u0627\u0644\u0625\u062f\u0627\u0631\u0629 \u0644\u0645\u0631\u0627\u062c\u0639\u0629 \u0627\u0644\u0642\u0627\u062f\u0629 \u0639\u0644\u0649 \u0623\u064a \u0645\u0633\u062a\u0648\u0649 \u0645\u0646 \u0645\u0633\u062a\u0648\u064a\u0627\u062a \u0627\u0644\u0625\u062f\u0627\u0631\u0629. \u064a\u0644\u062a\u0642\u0637 \u0627\u0644\u062a\u0639\u0644\u064a\u0642\u0627\u062a \u0627\u0644\u0633\u0631\u064a\u0629 \u0645\u0646 \u0627\u0644\u0645\u062f\u064a\u0631 \u0627\u0644\u0641\u0631\u062f\u064a \u0648\u0645\u062f\u064a\u0631\u0647 \/ \u0645\u062f\u064a\u0631\u0647\u0627 \u0648\u0623\u0642\u0631\u0627\u0646\u0647 \u0648\u0627\u0644\u062a\u0642\u064a\u064a\u0645 \u0627\u0644\u0634\u062e\u0635\u064a. \u064a\u0642\u062f\u0645 \u0627\u0644\u062a\u0642\u0631\u064a\u0631 \u0645\u0642\u064a\u0627\u0633\u0627 \u0644\u0645\u0648\u0642\u0641 \u0627\u0644\u0641\u0631\u062f \u0648\u0633\u0644\u0648\u0643\u0647 \u0648\u0623\u062f\u0627\u0626\u0647.<\/span><span style=\"font-size:9.0pt;line-height:107%\"><o:p><\/o:p><\/span><\/p>","icon":"20240625134854-HR Diagnostics image.png","is_active":0,"deleted_at":null,"created_at":"2024-06-25 13:48:54","updated_at":"2024-06-25 13:48:54"},{"id":4,"service":4,"approach":"<p>F<\/p>","approach_ar":"<p>F<\/p>","icon":"20240625175342-Screenshot_20230403-222907_LinkedIn.jpg","is_active":0,"deleted_at":null,"created_at":"2024-06-25 17:53:42","updated_at":"2024-06-25 17:53:42"},{"id":5,"service":1,"approach":"<p style=\"language:en-US;line-height:120%;margin-top:16.65pt;margin-bottom:\r\n0pt;margin-left:.01in;margin-right:.05in;text-indent:0in;text-align:justify;\r\ntext-justify:inter-ideograph;direction:ltr;unicode-bidi:embed;mso-vertical-align-alt:\r\nauto;mso-line-break-override:none;word-break:normal;punctuation-wrap:hanging\"><span style=\"font-size: 11pt; font-family: &quot;Segoe UI&quot;; font-variant-numeric: normal; font-variant-east-asian: normal; font-variant-alternates: normal; font-variant-position: normal; color: rgb(35, 31, 32); letter-spacing: 0.3pt; vertical-align: baseline;\">Engaging <\/span><span style=\"font-size: 11pt; font-family: &quot;Segoe UI&quot;; font-variant-numeric: normal; font-variant-east-asian: normal; font-variant-alternates: normal; font-variant-position: normal; color: rgb(35, 31, 32); letter-spacing: 0.24pt; vertical-align: baseline;\">the <\/span><span style=\"font-size: 11pt; font-family: &quot;Segoe UI&quot;; font-variant-numeric: normal; font-variant-east-asian: normal; font-variant-alternates: normal; font-variant-position: normal; color: rgb(35, 31, 32); letter-spacing: 0.3pt; vertical-align: baseline;\">heart <\/span><span style=\"font-size: 11pt; font-family: &quot;Segoe UI&quot;; font-variant-numeric: normal; font-variant-east-asian: normal; font-variant-alternates: normal; font-variant-position: normal; color: rgb(35, 31, 32); letter-spacing: -0.06pt; vertical-align: baseline;\">is <\/span><span style=\"font-size: 11pt; font-family: &quot;Segoe UI&quot;; font-variant-numeric: normal; font-variant-east-asian: normal; font-variant-alternates: normal; font-variant-position: normal; color: rgb(35, 31, 32); letter-spacing: 0.24pt; vertical-align: baseline;\">the <\/span><span style=\"font-size: 11pt; font-family: &quot;Segoe UI&quot;; font-variant-numeric: normal; font-variant-east-asian: normal; font-variant-alternates: normal; font-variant-position: normal; color: rgb(35, 31, 32); letter-spacing: 0.3pt; vertical-align: baseline;\">center <\/span><span style=\"font-size: 11pt; font-family: &quot;Segoe UI&quot;; font-variant-numeric: normal; font-variant-east-asian: normal; font-variant-alternates: normal; font-variant-position: normal; color: rgb(35, 31, 32); letter-spacing: 0pt; vertical-align: baseline;\">of <\/span><span style=\"font-size: 11pt; font-family: &quot;Segoe UI&quot;; font-variant-numeric: normal; font-variant-east-asian: normal; font-variant-alternates: normal; font-variant-position: normal; color: rgb(35, 31, 32); letter-spacing: 0.39pt; vertical-align: baseline;\">employee <\/span><span style=\"font-size: 11pt; font-family: &quot;Segoe UI&quot;; font-variant-numeric: normal; font-variant-east-asian: normal; font-variant-alternates: normal; font-variant-position: normal; color: rgb(35, 31, 32); letter-spacing: 0.36pt; vertical-align: baseline;\">engagement. <\/span><span style=\"font-size: 11pt; font-family: &quot;Segoe UI&quot;; font-variant-numeric: normal; font-variant-east-asian: normal; font-variant-alternates: normal; font-variant-position: normal; color: rgb(35, 31, 32); letter-spacing: 0.39pt; vertical-align: baseline;\">&nbsp;<\/span><span style=\"font-size: 11pt; font-family: &quot;Segoe UI&quot;; font-variant-numeric: normal; font-variant-east-asian: normal; font-variant-alternates: normal; font-variant-position: normal; color: rgb(35, 31, 32); letter-spacing: 0.49pt; vertical-align: baseline;\">When<\/span><span style=\"font-size: 11pt; font-family: &quot;Segoe UI&quot;; font-variant-numeric: normal; font-variant-east-asian: normal; font-variant-alternates: normal; font-variant-position: normal; color: rgb(35, 31, 32); letter-spacing: -0.69pt; vertical-align: baseline;\"> <\/span><span style=\"font-size: 11pt; font-family: &quot;Segoe UI&quot;; font-variant-numeric: normal; font-variant-east-asian: normal; font-variant-alternates: normal; font-variant-position: normal; color: rgb(35, 31, 32); letter-spacing: 0.24pt; vertical-align: baseline;\">the<\/span><span style=\"font-size: 11pt; font-family: &quot;Segoe UI&quot;; font-variant-numeric: normal; font-variant-east-asian: normal; font-variant-alternates: normal; font-variant-position: normal; color: rgb(35, 31, 32); letter-spacing: -0.69pt; vertical-align: baseline;\"> <\/span><span style=\"font-size: 11pt; font-family: &quot;Segoe UI&quot;; font-variant-numeric: normal; font-variant-east-asian: normal; font-variant-alternates: normal; font-variant-position: normal; color: rgb(35, 31, 32); letter-spacing: 0.3pt; vertical-align: baseline;\">heart<\/span><span style=\"font-size: 11pt; font-family: &quot;Segoe UI&quot;; font-variant-numeric: normal; font-variant-east-asian: normal; font-variant-alternates: normal; font-variant-position: normal; color: rgb(35, 31, 32); letter-spacing: -0.69pt; vertical-align: baseline;\"> <\/span><span style=\"font-size: 11pt; font-family: &quot;Segoe UI&quot;; font-variant-numeric: normal; font-variant-east-asian: normal; font-variant-alternates: normal; font-variant-position: normal; color: rgb(35, 31, 32); letter-spacing: -0.06pt; vertical-align: baseline;\">is<\/span><span style=\"font-size: 11pt; font-family: &quot;Segoe UI&quot;; font-variant-numeric: normal; font-variant-east-asian: normal; font-variant-alternates: normal; font-variant-position: normal; color: rgb(35, 31, 32); letter-spacing: -0.69pt; vertical-align: baseline;\"> <\/span><span style=\"font-size: 11pt; font-family: &quot;Segoe UI&quot;; font-variant-numeric: normal; font-variant-east-asian: normal; font-variant-alternates: normal; font-variant-position: normal; color: rgb(35, 31, 32); letter-spacing: 0.33pt; vertical-align: baseline;\">engaged,<\/span><span style=\"font-size: 11pt; font-family: &quot;Segoe UI&quot;; font-variant-numeric: normal; font-variant-east-asian: normal; font-variant-alternates: normal; font-variant-position: normal; color: rgb(35, 31, 32); letter-spacing: -0.69pt; vertical-align: baseline;\"> <\/span><span style=\"font-size: 11pt; font-family: &quot;Segoe UI&quot;; font-variant-numeric: normal; font-variant-east-asian: normal; font-variant-alternates: normal; font-variant-position: normal; color: rgb(35, 31, 32); letter-spacing: 0.24pt; vertical-align: baseline;\">the<\/span><span style=\"font-size: 11pt; font-family: &quot;Segoe UI&quot;; font-variant-numeric: normal; font-variant-east-asian: normal; font-variant-alternates: normal; font-variant-position: normal; color: rgb(35, 31, 32); letter-spacing: -0.69pt; vertical-align: baseline;\"> <\/span><span style=\"font-size: 11pt; font-family: &quot;Segoe UI&quot;; font-variant-numeric: normal; font-variant-east-asian: normal; font-variant-alternates: normal; font-variant-position: normal; color: rgb(35, 31, 32); letter-spacing: 0.3pt; vertical-align: baseline;\">mind<\/span><span style=\"font-size: 11pt; font-family: &quot;Segoe UI&quot;; font-variant-numeric: normal; font-variant-east-asian: normal; font-variant-alternates: normal; font-variant-position: normal; color: rgb(35, 31, 32); letter-spacing: -0.69pt; vertical-align: baseline;\"> <\/span><span style=\"font-size: 11pt; font-family: &quot;Segoe UI&quot;; font-variant-numeric: normal; font-variant-east-asian: normal; font-variant-alternates: normal; font-variant-position: normal; color: rgb(35, 31, 32); letter-spacing: -0.12pt; vertical-align: baseline;\">will<\/span><span style=\"font-size: 11pt; font-family: &quot;Segoe UI&quot;; font-variant-numeric: normal; font-variant-east-asian: normal; font-variant-alternates: normal; font-variant-position: normal; color: rgb(35, 31, 32); letter-spacing: -0.69pt; vertical-align: baseline;\"> <\/span><span style=\"font-size: 11pt; font-family: &quot;Segoe UI&quot;; font-variant-numeric: normal; font-variant-east-asian: normal; font-variant-alternates: normal; font-variant-position: normal; color: rgb(35, 31, 32); letter-spacing: 0.49pt; vertical-align: baseline;\">be<\/span><span style=\"font-size: 11pt; font-family: &quot;Segoe UI&quot;; font-variant-numeric: normal; font-variant-east-asian: normal; font-variant-alternates: normal; font-variant-position: normal; color: rgb(35, 31, 32); letter-spacing: -0.69pt; vertical-align: baseline;\"> <\/span><span style=\"font-size: 11pt; font-family: &quot;Segoe UI&quot;; font-variant-numeric: normal; font-variant-east-asian: normal; font-variant-alternates: normal; font-variant-position: normal; color: rgb(35, 31, 32); letter-spacing: 0.24pt; vertical-align: baseline;\">stimulated<\/span><span style=\"font-size: 11pt; font-family: &quot;Segoe UI&quot;; font-variant-numeric: normal; font-variant-east-asian: normal; font-variant-alternates: normal; font-variant-position: normal; color: rgb(35, 31, 32); letter-spacing: -0.69pt; vertical-align: baseline;\"> <\/span><span style=\"font-size: 11pt; font-family: &quot;Segoe UI&quot;; font-variant-numeric: normal; font-variant-east-asian: normal; font-variant-alternates: normal; font-variant-position: normal; color: rgb(35, 31, 32); letter-spacing: 0.12pt; vertical-align: baseline;\">to<\/span><span style=\"font-size: 11pt; font-family: &quot;Segoe UI&quot;; font-variant-numeric: normal; font-variant-east-asian: normal; font-variant-alternates: normal; font-variant-position: normal; color: rgb(35, 31, 32); letter-spacing: -0.69pt; vertical-align: baseline;\"> <\/span><span style=\"font-size: 11pt; font-family: &quot;Segoe UI&quot;; font-variant-numeric: normal; font-variant-east-asian: normal; font-variant-alternates: normal; font-variant-position: normal; color: rgb(35, 31, 32); letter-spacing: -0.18pt; vertical-align: baseline;\">think. <\/span><span style=\"font-size: 11pt; font-family: &quot;Segoe UI&quot;; font-variant-numeric: normal; font-variant-east-asian: normal; font-variant-alternates: normal; font-variant-position: normal; color: rgb(35, 31, 32); letter-spacing: -2.24pt; vertical-align: baseline;\">&nbsp;<\/span><span style=\"font-size:11.0pt;font-family:&quot;Segoe UI&quot;;mso-ascii-font-family:&quot;Segoe UI&quot;;\r\nmso-fareast-font-family:+mn-ea;mso-bidi-font-family:&quot;Segoe UI&quot;;mso-fareast-theme-font:\r\nminor-fareast;color:#231F20;letter-spacing:.3pt;mso-font-kerning:12.0pt;\r\nlanguage:en-US;mso-style-textfill-type:solid;mso-style-textfill-fill-color:\r\n#231F20;mso-style-textfill-fill-alpha:100.0%\">When the heart and mind are\r\nactive, the human<\/span><span style=\"font-size:11.0pt;font-family:&quot;Segoe UI&quot;;\r\nmso-ascii-font-family:&quot;Segoe UI&quot;;mso-fareast-font-family:+mn-ea;mso-bidi-font-family:\r\n&quot;Segoe UI&quot;;mso-fareast-theme-font:minor-fareast;color:#231F20;letter-spacing:\r\n.3pt;mso-font-kerning:12.0pt;language:en-US;mso-style-textfill-type:solid;\r\nmso-style-textfill-fill-color:#231F20;mso-style-textfill-fill-alpha:100.0%\">-<\/span><span style=\"font-size:11.0pt;font-family:&quot;Segoe UI&quot;;mso-ascii-font-family:&quot;Segoe UI&quot;;\r\nmso-fareast-font-family:+mn-ea;mso-bidi-font-family:&quot;Segoe UI&quot;;mso-fareast-theme-font:\r\nminor-fareast;color:#231F20;letter-spacing:.3pt;mso-font-kerning:12.0pt;\r\nlanguage:en-US;mso-style-textfill-type:solid;mso-style-textfill-fill-color:\r\n#231F20;mso-style-textfill-fill-alpha:100.0%\">being <\/span><span style=\"font-size:11.0pt;font-family:&quot;Segoe UI&quot;;mso-ascii-font-family:&quot;Segoe UI&quot;;\r\nmso-fareast-font-family:+mn-ea;mso-bidi-font-family:&quot;Segoe UI&quot;;mso-fareast-theme-font:\r\nminor-fareast;color:#231F20;letter-spacing:.3pt;mso-font-kerning:12.0pt;\r\nlanguage:en-US;mso-style-textfill-type:solid;mso-style-textfill-fill-color:\r\n#231F20;mso-style-textfill-fill-alpha:100.0%\">is ready to contribute (<\/span><span style=\"font-size:11.0pt;font-family:&quot;Segoe UI&quot;;mso-ascii-font-family:&quot;Segoe UI&quot;;\r\nmso-fareast-font-family:+mn-ea;mso-bidi-font-family:&quot;Segoe UI&quot;;mso-fareast-theme-font:\r\nminor-fareast;color:#231F20;letter-spacing:.3pt;mso-font-kerning:12.0pt;\r\nlanguage:en-US;mso-style-textfill-type:solid;mso-style-textfill-fill-color:\r\n#231F20;mso-style-textfill-fill-alpha:100.0%\">give hand<\/span><span style=\"font-size:11.0pt;font-family:&quot;Segoe UI&quot;;mso-ascii-font-family:&quot;Segoe UI&quot;;\r\nmso-fareast-font-family:+mn-ea;mso-bidi-font-family:&quot;Segoe UI&quot;;mso-fareast-theme-font:\r\nminor-fareast;color:#231F20;letter-spacing:.3pt;mso-font-kerning:12.0pt;\r\nlanguage:en-US;mso-style-textfill-type:solid;mso-style-textfill-fill-color:\r\n#231F20;mso-style-textfill-fill-alpha:100.0%\">) if enabled<\/span><span style=\"font-size:11.0pt;font-family:&quot;Segoe UI&quot;;mso-ascii-font-family:&quot;Segoe UI&quot;;\r\nmso-fareast-font-family:+mn-ea;mso-bidi-font-family:&quot;Segoe UI&quot;;mso-fareast-theme-font:\r\nminor-fareast;color:#231F20;letter-spacing:.3pt;mso-font-kerning:12.0pt;\r\nlanguage:en-US;mso-style-textfill-type:solid;mso-style-textfill-fill-color:\r\n#231F20;mso-style-textfill-fill-alpha:100.0%\">.<\/span><\/p>","approach_ar":"<p><span style=\"font-variant-numeric: normal; font-variant-east-asian: normal; font-variant-alternates: normal; font-variant-position: normal; text-align: justify; font-size: 11pt; font-family: &quot;Segoe UI&quot;; color: rgb(35, 31, 32); letter-spacing: 0.3pt; vertical-align: baseline;\">Engaging&nbsp;<\/span><span style=\"font-variant-numeric: normal; font-variant-east-asian: normal; font-variant-alternates: normal; font-variant-position: normal; text-align: justify; font-size: 11pt; font-family: &quot;Segoe UI&quot;; color: rgb(35, 31, 32); letter-spacing: 0.24pt; vertical-align: baseline;\">the&nbsp;<\/span><span style=\"font-variant-numeric: normal; font-variant-east-asian: normal; font-variant-alternates: normal; font-variant-position: normal; text-align: justify; font-size: 11pt; font-family: &quot;Segoe UI&quot;; color: rgb(35, 31, 32); letter-spacing: 0.3pt; vertical-align: baseline;\">heart&nbsp;<\/span><span style=\"font-variant-numeric: normal; font-variant-east-asian: normal; font-variant-alternates: normal; font-variant-position: normal; text-align: justify; font-size: 11pt; font-family: &quot;Segoe UI&quot;; color: rgb(35, 31, 32); letter-spacing: -0.06pt; vertical-align: baseline;\">is&nbsp;<\/span><span style=\"font-variant-numeric: normal; font-variant-east-asian: normal; font-variant-alternates: normal; font-variant-position: normal; text-align: justify; font-size: 11pt; font-family: &quot;Segoe UI&quot;; color: rgb(35, 31, 32); letter-spacing: 0.24pt; vertical-align: baseline;\">the&nbsp;<\/span><span style=\"font-variant-numeric: normal; font-variant-east-asian: normal; font-variant-alternates: normal; font-variant-position: normal; text-align: justify; font-size: 11pt; font-family: &quot;Segoe UI&quot;; color: rgb(35, 31, 32); letter-spacing: 0.3pt; vertical-align: baseline;\">center&nbsp;<\/span><span style=\"font-variant-numeric: normal; font-variant-east-asian: normal; font-variant-alternates: normal; font-variant-position: normal; letter-spacing: 0pt; text-align: justify; font-size: 11pt; font-family: &quot;Segoe UI&quot;; color: rgb(35, 31, 32); vertical-align: baseline;\">of&nbsp;<\/span><span style=\"font-variant-numeric: normal; font-variant-east-asian: normal; font-variant-alternates: normal; font-variant-position: normal; text-align: justify; font-size: 11pt; font-family: &quot;Segoe UI&quot;; color: rgb(35, 31, 32); letter-spacing: 0.39pt; vertical-align: baseline;\">employee&nbsp;<\/span><span style=\"font-variant-numeric: normal; font-variant-east-asian: normal; font-variant-alternates: normal; font-variant-position: normal; text-align: justify; font-size: 11pt; font-family: &quot;Segoe UI&quot;; color: rgb(35, 31, 32); letter-spacing: 0.36pt; vertical-align: baseline;\">engagement.&nbsp;<\/span><span style=\"font-variant-numeric: normal; font-variant-east-asian: normal; font-variant-alternates: normal; font-variant-position: normal; text-align: justify; font-size: 11pt; font-family: &quot;Segoe UI&quot;; color: rgb(35, 31, 32); letter-spacing: 0.39pt; vertical-align: baseline;\">&nbsp;<\/span><span style=\"font-variant-numeric: normal; font-variant-east-asian: normal; font-variant-alternates: normal; font-variant-position: normal; text-align: justify; font-size: 11pt; font-family: &quot;Segoe UI&quot;; color: rgb(35, 31, 32); letter-spacing: 0.49pt; vertical-align: baseline;\">When<\/span><span style=\"font-variant-numeric: normal; font-variant-east-asian: normal; font-variant-alternates: normal; font-variant-position: normal; text-align: justify; font-size: 11pt; font-family: &quot;Segoe UI&quot;; color: rgb(35, 31, 32); letter-spacing: -0.69pt; vertical-align: baseline;\">&nbsp;<\/span><span style=\"font-variant-numeric: normal; font-variant-east-asian: normal; font-variant-alternates: normal; font-variant-position: normal; text-align: justify; font-size: 11pt; font-family: &quot;Segoe UI&quot;; color: rgb(35, 31, 32); letter-spacing: 0.24pt; vertical-align: baseline;\">the<\/span><span style=\"font-variant-numeric: normal; font-variant-east-asian: normal; font-variant-alternates: normal; font-variant-position: normal; text-align: justify; font-size: 11pt; font-family: &quot;Segoe UI&quot;; color: rgb(35, 31, 32); letter-spacing: -0.69pt; vertical-align: baseline;\">&nbsp;<\/span><span style=\"font-variant-numeric: normal; font-variant-east-asian: normal; font-variant-alternates: normal; font-variant-position: normal; text-align: justify; font-size: 11pt; font-family: &quot;Segoe UI&quot;; color: rgb(35, 31, 32); letter-spacing: 0.3pt; vertical-align: baseline;\">heart<\/span><span style=\"font-variant-numeric: normal; font-variant-east-asian: normal; font-variant-alternates: normal; font-variant-position: normal; text-align: justify; font-size: 11pt; font-family: &quot;Segoe UI&quot;; color: rgb(35, 31, 32); letter-spacing: -0.69pt; vertical-align: baseline;\">&nbsp;<\/span><span style=\"font-variant-numeric: normal; font-variant-east-asian: normal; font-variant-alternates: normal; font-variant-position: normal; text-align: justify; font-size: 11pt; font-family: &quot;Segoe UI&quot;; color: rgb(35, 31, 32); letter-spacing: -0.06pt; vertical-align: baseline;\">is<\/span><span style=\"font-variant-numeric: normal; font-variant-east-asian: normal; font-variant-alternates: normal; font-variant-position: normal; text-align: justify; font-size: 11pt; font-family: &quot;Segoe UI&quot;; color: rgb(35, 31, 32); letter-spacing: -0.69pt; vertical-align: baseline;\">&nbsp;<\/span><span style=\"font-variant-numeric: normal; font-variant-east-asian: normal; font-variant-alternates: normal; font-variant-position: normal; text-align: justify; font-size: 11pt; font-family: &quot;Segoe UI&quot;; color: rgb(35, 31, 32); letter-spacing: 0.33pt; vertical-align: baseline;\">engaged,<\/span><span style=\"font-variant-numeric: normal; font-variant-east-asian: normal; font-variant-alternates: normal; font-variant-position: normal; text-align: justify; font-size: 11pt; font-family: &quot;Segoe UI&quot;; color: rgb(35, 31, 32); letter-spacing: -0.69pt; vertical-align: baseline;\">&nbsp;<\/span><span style=\"font-variant-numeric: normal; font-variant-east-asian: normal; font-variant-alternates: normal; font-variant-position: normal; text-align: justify; font-size: 11pt; font-family: &quot;Segoe UI&quot;; color: rgb(35, 31, 32); letter-spacing: 0.24pt; vertical-align: baseline;\">the<\/span><span style=\"font-variant-numeric: normal; font-variant-east-asian: normal; font-variant-alternates: normal; font-variant-position: normal; text-align: justify; font-size: 11pt; font-family: &quot;Segoe UI&quot;; color: rgb(35, 31, 32); letter-spacing: -0.69pt; vertical-align: baseline;\">&nbsp;<\/span><span style=\"font-variant-numeric: normal; font-variant-east-asian: normal; font-variant-alternates: normal; font-variant-position: normal; text-align: justify; font-size: 11pt; font-family: &quot;Segoe UI&quot;; color: rgb(35, 31, 32); letter-spacing: 0.3pt; vertical-align: baseline;\">mind<\/span><span style=\"font-variant-numeric: normal; font-variant-east-asian: normal; font-variant-alternates: normal; font-variant-position: normal; text-align: justify; font-size: 11pt; font-family: &quot;Segoe UI&quot;; color: rgb(35, 31, 32); letter-spacing: -0.69pt; vertical-align: baseline;\">&nbsp;<\/span><span style=\"font-variant-numeric: normal; font-variant-east-asian: normal; font-variant-alternates: normal; font-variant-position: normal; text-align: justify; font-size: 11pt; font-family: &quot;Segoe UI&quot;; color: rgb(35, 31, 32); letter-spacing: -0.12pt; vertical-align: baseline;\">will<\/span><span style=\"font-variant-numeric: normal; font-variant-east-asian: normal; font-variant-alternates: normal; font-variant-position: normal; text-align: justify; font-size: 11pt; font-family: &quot;Segoe UI&quot;; color: rgb(35, 31, 32); letter-spacing: -0.69pt; vertical-align: baseline;\">&nbsp;<\/span><span style=\"font-variant-numeric: normal; font-variant-east-asian: normal; font-variant-alternates: normal; font-variant-position: normal; text-align: justify; font-size: 11pt; font-family: &quot;Segoe UI&quot;; color: rgb(35, 31, 32); letter-spacing: 0.49pt; vertical-align: baseline;\">be<\/span><span style=\"font-variant-numeric: normal; font-variant-east-asian: normal; font-variant-alternates: normal; font-variant-position: normal; text-align: justify; font-size: 11pt; font-family: &quot;Segoe UI&quot;; color: rgb(35, 31, 32); letter-spacing: -0.69pt; vertical-align: baseline;\">&nbsp;<\/span><span style=\"font-variant-numeric: normal; font-variant-east-asian: normal; font-variant-alternates: normal; font-variant-position: normal; text-align: justify; font-size: 11pt; font-family: &quot;Segoe UI&quot;; color: rgb(35, 31, 32); letter-spacing: 0.24pt; vertical-align: baseline;\">stimulated<\/span><span style=\"font-variant-numeric: normal; font-variant-east-asian: normal; font-variant-alternates: normal; font-variant-position: normal; text-align: justify; font-size: 11pt; font-family: &quot;Segoe UI&quot;; color: rgb(35, 31, 32); letter-spacing: -0.69pt; vertical-align: baseline;\">&nbsp;<\/span><span style=\"font-variant-numeric: normal; font-variant-east-asian: normal; font-variant-alternates: normal; font-variant-position: normal; text-align: justify; font-size: 11pt; font-family: &quot;Segoe UI&quot;; color: rgb(35, 31, 32); letter-spacing: 0.12pt; vertical-align: baseline;\">to<\/span><span style=\"font-variant-numeric: normal; font-variant-east-asian: normal; font-variant-alternates: normal; font-variant-position: normal; text-align: justify; font-size: 11pt; font-family: &quot;Segoe UI&quot;; color: rgb(35, 31, 32); letter-spacing: -0.69pt; vertical-align: baseline;\">&nbsp;<\/span><span style=\"font-variant-numeric: normal; font-variant-east-asian: normal; font-variant-alternates: normal; font-variant-position: normal; text-align: justify; font-size: 11pt; font-family: &quot;Segoe UI&quot;; color: rgb(35, 31, 32); letter-spacing: -0.18pt; vertical-align: baseline;\">think.&nbsp;<\/span><span style=\"font-variant-numeric: normal; font-variant-east-asian: normal; font-variant-alternates: normal; font-variant-position: normal; text-align: justify; font-size: 11pt; font-family: &quot;Segoe UI&quot;; color: rgb(35, 31, 32); letter-spacing: -2.24pt; vertical-align: baseline;\">&nbsp;<\/span><span style=\"text-align: justify; font-size: 11pt; font-family: &quot;Segoe UI&quot;; color: rgb(35, 31, 32); letter-spacing: 0.3pt;\">When the heart and mind are active, the human<\/span><span style=\"text-align: justify; font-size: 11pt; font-family: &quot;Segoe UI&quot;; color: rgb(35, 31, 32); letter-spacing: 0.3pt;\">-<\/span><span style=\"text-align: justify; font-size: 11pt; font-family: &quot;Segoe UI&quot;; color: rgb(35, 31, 32); letter-spacing: 0.3pt;\">being&nbsp;<\/span><span style=\"text-align: justify; font-size: 11pt; font-family: &quot;Segoe UI&quot;; color: rgb(35, 31, 32); letter-spacing: 0.3pt;\">is ready to contribute (<\/span><span style=\"text-align: justify; font-size: 11pt; font-family: &quot;Segoe UI&quot;; color: rgb(35, 31, 32); letter-spacing: 0.3pt;\">give hand<\/span><span style=\"text-align: justify; font-size: 11pt; font-family: &quot;Segoe UI&quot;; color: rgb(35, 31, 32); letter-spacing: 0.3pt;\">) if enabled<\/span><span style=\"text-align: justify; font-size: 11pt; font-family: &quot;Segoe UI&quot;; color: rgb(35, 31, 32); letter-spacing: 0.3pt;\">.<\/span><br><\/p>","icon":"1720073203.png","is_active":0,"deleted_at":null,"created_at":"2024-07-04 10:06:43","updated_at":"2024-07-04 10:06:43"},{"id":6,"service":1,"approach":"<p style=\"line-height: normal; margin: 2.27pt 0in 0pt 0.01in; text-indent: 0in; direction: ltr; unicode-bidi: embed; word-break: normal;\"><span style=\"font-size: 10pt; font-family: &quot;Segoe UI&quot;; font-variant-numeric: normal; font-variant-east-asian: normal; font-variant-alternates: normal; font-variant-position: normal; color: rgb(35, 31, 32); letter-spacing: 0.24pt; font-weight: bold; vertical-align: baseline;\">Employee<\/span><span style=\"font-size: 10pt; font-family: &quot;Segoe UI&quot;; font-variant-numeric: normal; font-variant-east-asian: normal; font-variant-alternates: normal; font-variant-position: normal; color: rgb(35, 31, 32); letter-spacing: -1.21pt; font-weight: bold; vertical-align: baseline;\"> <\/span><span style=\"font-size: 10pt; font-family: &quot;Segoe UI&quot;; font-variant-numeric: normal; font-variant-east-asian: normal; font-variant-alternates: normal; font-variant-position: normal; color: rgb(35, 31, 32); letter-spacing: 0.21pt; font-weight: bold; vertical-align: baseline;\">Engagement:<\/span><\/p><p style=\"line-height: normal; margin: 2.27pt 0in 0pt 0.01in; text-indent: 0in; direction: ltr; unicode-bidi: embed; word-break: normal;\"><\/p><p>\r\n\r\n\r\n\r\n<\/p><p style=\"language:en-US;line-height:120%;margin-top:0pt;margin-bottom:0pt;\r\nmargin-left:.01in;margin-right:0in;text-indent:0in;text-align:justify;\r\ntext-justify:inter-ideograph;direction:ltr;unicode-bidi:embed;mso-vertical-align-alt:\r\nauto;mso-line-break-override:none;word-break:normal;punctuation-wrap:hanging\"><span style=\"font-size: 10pt; font-family: &quot;Segoe UI&quot;; font-variant-numeric: normal; font-variant-east-asian: normal; font-variant-alternates: normal; font-variant-position: normal; color: rgb(35, 31, 32); letter-spacing: 0.03pt; vertical-align: baseline;\">The<\/span><span style=\"font-size: 10pt; font-family: &quot;Segoe UI&quot;; font-variant-numeric: normal; font-variant-east-asian: normal; font-variant-alternates: normal; font-variant-position: normal; color: rgb(35, 31, 32); letter-spacing: 0.06pt; vertical-align: baseline;\"> <\/span><span style=\"font-size: 10pt; font-family: &quot;Segoe UI&quot;; font-variant-numeric: normal; font-variant-east-asian: normal; font-variant-alternates: normal; font-variant-position: normal; color: rgb(35, 31, 32); letter-spacing: 0.15pt; vertical-align: baseline;\">emotional,<\/span><span style=\"font-size: 10pt; font-family: &quot;Segoe UI&quot;; font-variant-numeric: normal; font-variant-east-asian: normal; font-variant-alternates: normal; font-variant-position: normal; color: rgb(35, 31, 32); letter-spacing: 0.09pt; vertical-align: baseline;\"> <\/span><span style=\"font-size: 10pt; font-family: &quot;Segoe UI&quot;; font-variant-numeric: normal; font-variant-east-asian: normal; font-variant-alternates: normal; font-variant-position: normal; color: rgb(35, 31, 32); letter-spacing: 0.36pt; vertical-align: baseline;\">mental<\/span><span style=\"font-size: 10pt; font-family: &quot;Segoe UI&quot;; font-variant-numeric: normal; font-variant-east-asian: normal; font-variant-alternates: normal; font-variant-position: normal; color: rgb(35, 31, 32); letter-spacing: 0.36pt; vertical-align: baseline;\">,<\/span><span style=\"font-size: 10pt; font-family: &quot;Segoe UI&quot;; font-variant-numeric: normal; font-variant-east-asian: normal; font-variant-alternates: normal; font-variant-position: normal; color: rgb(35, 31, 32); letter-spacing: 0.09pt; vertical-align: baseline;\"> <\/span><span style=\"font-size: 10pt; font-family: &quot;Segoe UI&quot;; font-variant-numeric: normal; font-variant-east-asian: normal; font-variant-alternates: normal; font-variant-position: normal; color: rgb(35, 31, 32); letter-spacing: 0.55pt; vertical-align: baseline;\">and<\/span><span style=\"font-size: 10pt; font-family: &quot;Segoe UI&quot;; font-variant-numeric: normal; font-variant-east-asian: normal; font-variant-alternates: normal; font-variant-position: normal; color: rgb(35, 31, 32); letter-spacing: 0.09pt; vertical-align: baseline;\"> <\/span><span style=\"font-size: 10pt; font-family: &quot;Segoe UI&quot;; font-variant-numeric: normal; font-variant-east-asian: normal; font-variant-alternates: normal; font-variant-position: normal; color: rgb(35, 31, 32); letter-spacing: 0.27pt; vertical-align: baseline;\">physical<\/span><span style=\"font-size: 10pt; font-family: &quot;Segoe UI&quot;; font-variant-numeric: normal; font-variant-east-asian: normal; font-variant-alternates: normal; font-variant-position: normal; color: rgb(35, 31, 32); letter-spacing: 0.09pt; vertical-align: baseline;\"> <\/span><span style=\"font-size: 10pt; font-family: &quot;Segoe UI&quot;; font-variant-numeric: normal; font-variant-east-asian: normal; font-variant-alternates: normal; font-variant-position: normal; color: rgb(35, 31, 32); letter-spacing: 0.27pt; vertical-align: baseline;\">connection<\/span><span style=\"font-size: 10pt; font-family: &quot;Segoe UI&quot;; font-variant-numeric: normal; font-variant-east-asian: normal; font-variant-alternates: normal; font-variant-position: normal; color: rgb(35, 31, 32); letter-spacing: 0.09pt; vertical-align: baseline;\"> <\/span><span style=\"font-size: 10pt; font-family: &quot;Segoe UI&quot;; font-variant-numeric: normal; font-variant-east-asian: normal; font-variant-alternates: normal; font-variant-position: normal; color: rgb(35, 31, 32); letter-spacing: 0pt; vertical-align: baseline;\">of<\/span><span style=\"font-size: 10pt; font-family: &quot;Segoe UI&quot;; font-variant-numeric: normal; font-variant-east-asian: normal; font-variant-alternates: normal; font-variant-position: normal; color: rgb(35, 31, 32); letter-spacing: 0pt; vertical-align: baseline;\"> <\/span><span style=\"font-size: 10pt; font-family: &quot;Segoe UI&quot;; font-variant-numeric: normal; font-variant-east-asian: normal; font-variant-alternates: normal; font-variant-position: normal; color: rgb(35, 31, 32); letter-spacing: 0.55pt; vertical-align: baseline;\">employees <\/span><span style=\"font-size: 10pt; font-family: &quot;Segoe UI&quot;; font-variant-numeric: normal; font-variant-east-asian: normal; font-variant-alternates: normal; font-variant-position: normal; color: rgb(35, 31, 32); letter-spacing: 0.21pt; vertical-align: baseline;\">to <\/span><span style=\"font-size: 10pt; font-family: &quot;Segoe UI&quot;; font-variant-numeric: normal; font-variant-east-asian: normal; font-variant-alternates: normal; font-variant-position: normal; color: rgb(35, 31, 32); letter-spacing: 0.36pt; vertical-align: baseline;\">the <\/span><span style=\"font-size: 10pt; font-family: &quot;Segoe UI&quot;; font-variant-numeric: normal; font-variant-east-asian: normal; font-variant-alternates: normal; font-variant-position: normal; color: rgb(35, 31, 32); letter-spacing: 0.33pt; vertical-align: baseline;\">organization <\/span><span style=\"font-size: 10pt; font-family: &quot;Segoe UI&quot;; font-variant-numeric: normal; font-variant-east-asian: normal; font-variant-alternates: normal; font-variant-position: normal; color: rgb(35, 31, 32); letter-spacing: 0.42pt; vertical-align: baseline;\">that <\/span><span style=\"font-size:10.0pt;\r\nfont-family:&quot;Segoe UI&quot;;mso-ascii-font-family:&quot;Segoe UI&quot;;mso-fareast-font-family:\r\n+mn-ea;mso-bidi-font-family:&quot;Segoe UI&quot;;mso-fareast-theme-font:minor-fareast;\r\ncolor:#231F20;letter-spacing:.33pt;mso-font-kerning:12.0pt;language:en-US;\r\nmso-style-textfill-type:solid;mso-style-textfill-fill-color:#231F20;mso-style-textfill-fill-alpha:\r\n100.0%\">stimulates<\/span><span style=\"font-size: 10pt; font-family: &quot;Segoe UI&quot;; font-variant-numeric: normal; font-variant-east-asian: normal; font-variant-alternates: normal; font-variant-position: normal; color: rgb(35, 31, 32); letter-spacing: 0.33pt; vertical-align: baseline;\"> <\/span><span style=\"font-size: 10pt; font-family: &quot;Segoe UI&quot;; font-variant-numeric: normal; font-variant-east-asian: normal; font-variant-alternates: normal; font-variant-position: normal; color: rgb(35, 31, 32); letter-spacing: 0.69pt; vertical-align: baseline;\">an<\/span><span style=\"font-size: 10pt; font-family: &quot;Segoe UI&quot;; font-variant-numeric: normal; font-variant-east-asian: normal; font-variant-alternates: normal; font-variant-position: normal; color: rgb(35, 31, 32); letter-spacing: 0.69pt; vertical-align: baseline;\"> <\/span><span style=\"font-size: 10pt; font-family: &quot;Segoe UI&quot;; font-variant-numeric: normal; font-variant-east-asian: normal; font-variant-alternates: normal; font-variant-position: normal; color: rgb(35, 31, 32); letter-spacing: 0.15pt; vertical-align: baseline;\">extraordinary<\/span><span style=\"font-size: 10pt; font-family: &quot;Segoe UI&quot;; font-variant-numeric: normal; font-variant-east-asian: normal; font-variant-alternates: normal; font-variant-position: normal; color: rgb(35, 31, 32); letter-spacing: -0.88pt; vertical-align: baseline;\"> <\/span><span style=\"font-size: 10pt; font-family: &quot;Segoe UI&quot;; font-variant-numeric: normal; font-variant-east-asian: normal; font-variant-alternates: normal; font-variant-position: normal; color: rgb(35, 31, 32); letter-spacing: 0.12pt; vertical-align: baseline;\">contribution<\/span><span style=\"font-size: 10pt; font-family: &quot;Segoe UI&quot;; font-variant-numeric: normal; font-variant-east-asian: normal; font-variant-alternates: normal; font-variant-position: normal; color: rgb(35, 31, 32); letter-spacing: -0.88pt; vertical-align: baseline;\"> <\/span><span style=\"font-size: 10pt; font-family: &quot;Segoe UI&quot;; font-variant-numeric: normal; font-variant-east-asian: normal; font-variant-alternates: normal; font-variant-position: normal; color: rgb(35, 31, 32); letter-spacing: 0.27pt; vertical-align: baseline;\">that<\/span><span style=\"font-size: 10pt; font-family: &quot;Segoe UI&quot;; font-variant-numeric: normal; font-variant-east-asian: normal; font-variant-alternates: normal; font-variant-position: normal; color: rgb(35, 31, 32); letter-spacing: -0.88pt; vertical-align: baseline;\"> <\/span><span style=\"font-size: 10pt; font-family: &quot;Segoe UI&quot;; font-variant-numeric: normal; font-variant-east-asian: normal; font-variant-alternates: normal; font-variant-position: normal; color: rgb(35, 31, 32); letter-spacing: 0.39pt; vertical-align: baseline;\">achieves<\/span><span style=\"font-size: 10pt; font-family: &quot;Segoe UI&quot;; font-variant-numeric: normal; font-variant-east-asian: normal; font-variant-alternates: normal; font-variant-position: normal; color: rgb(35, 31, 32); letter-spacing: -0.88pt; vertical-align: baseline;\"> <\/span><span style=\"font-size: 10pt; font-family: &quot;Segoe UI&quot;; font-variant-numeric: normal; font-variant-east-asian: normal; font-variant-alternates: normal; font-variant-position: normal; color: rgb(35, 31, 32); letter-spacing: 0.97pt; vertical-align: baseline;\">a<\/span><span style=\"font-size: 10pt; font-family: &quot;Segoe UI&quot;; font-variant-numeric: normal; font-variant-east-asian: normal; font-variant-alternates: normal; font-variant-position: normal; color: rgb(35, 31, 32); letter-spacing: 0.97pt; vertical-align: baseline;\"> <\/span><span style=\"font-size: 10pt; font-family: &quot;Segoe UI&quot;; font-variant-numeric: normal; font-variant-east-asian: normal; font-variant-alternates: normal; font-variant-position: normal; color: rgb(35, 31, 32); letter-spacing: 0.09pt; vertical-align: baseline;\">win-win<\/span><span style=\"font-size: 10pt; font-family: &quot;Segoe UI&quot;; font-variant-numeric: normal; font-variant-east-asian: normal; font-variant-alternates: normal; font-variant-position: normal; color: rgb(35, 31, 32); letter-spacing: -0.12pt; vertical-align: baseline;\"> <\/span><span style=\"font-size: 10pt; font-family: &quot;Segoe UI&quot;; font-variant-numeric: normal; font-variant-east-asian: normal; font-variant-alternates: normal; font-variant-position: normal; color: rgb(35, 31, 32); letter-spacing: 0.12pt; vertical-align: baseline;\">situation<\/span><span style=\"font-size: 10pt; font-family: &quot;Segoe UI&quot;; font-variant-numeric: normal; font-variant-east-asian: normal; font-variant-alternates: normal; font-variant-position: normal; color: rgb(35, 31, 32); letter-spacing: -0.12pt; vertical-align: baseline;\">;<\/span><span style=\"font-size: 10pt; font-family: &quot;Segoe UI&quot;; font-variant-numeric: normal; font-variant-east-asian: normal; font-variant-alternates: normal; font-variant-position: normal; color: rgb(35, 31, 32); letter-spacing: -0.09pt; vertical-align: baseline;\"> <\/span><span style=\"font-size: 10pt; font-family: &quot;Segoe UI&quot;; font-variant-numeric: normal; font-variant-east-asian: normal; font-variant-alternates: normal; font-variant-position: normal; color: rgb(35, 31, 32); letter-spacing: 0.18pt; vertical-align: baseline;\">better<\/span><span style=\"font-size: 10pt; font-family: &quot;Segoe UI&quot;; font-variant-numeric: normal; font-variant-east-asian: normal; font-variant-alternates: normal; font-variant-position: normal; color: rgb(35, 31, 32); letter-spacing: -0.09pt; vertical-align: baseline;\"> <\/span><span style=\"font-size: 10pt; font-family: &quot;Segoe UI&quot;; font-variant-numeric: normal; font-variant-east-asian: normal; font-variant-alternates: normal; font-variant-position: normal; color: rgb(35, 31, 32); letter-spacing: 0.39pt; vertical-align: baseline;\">employee<\/span><span style=\"font-size: 10pt; font-family: &quot;Segoe UI&quot;; font-variant-numeric: normal; font-variant-east-asian: normal; font-variant-alternates: normal; font-variant-position: normal; color: rgb(35, 31, 32); letter-spacing: -0.12pt; vertical-align: baseline;\"> <\/span><span style=\"font-size: 10pt; font-family: &quot;Segoe UI&quot;; font-variant-numeric: normal; font-variant-east-asian: normal; font-variant-alternates: normal; font-variant-position: normal; color: rgb(35, 31, 32); letter-spacing: 0.3pt; vertical-align: baseline;\">experience <\/span><span style=\"font-size: 10pt; font-family: &quot;Segoe UI&quot;; font-variant-numeric: normal; font-variant-east-asian: normal; font-variant-alternates: normal; font-variant-position: normal; color: rgb(35, 31, 32); letter-spacing: 0.55pt; vertical-align: baseline;\">and<\/span><span style=\"font-size: 10pt; font-family: &quot;Segoe UI&quot;; font-variant-numeric: normal; font-variant-east-asian: normal; font-variant-alternates: normal; font-variant-position: normal; color: rgb(35, 31, 32); letter-spacing: 0.55pt; vertical-align: baseline;\"> better<\/span><span style=\"font-size: 10pt; font-family: &quot;Segoe UI&quot;; font-variant-numeric: normal; font-variant-east-asian: normal; font-variant-alternates: normal; font-variant-position: normal; color: rgb(35, 31, 32); letter-spacing: -1.12pt; vertical-align: baseline;\"> <\/span><span style=\"font-size: 10pt; font-family: &quot;Segoe UI&quot;; font-variant-numeric: normal; font-variant-east-asian: normal; font-variant-alternates: normal; font-variant-position: normal; color: rgb(35, 31, 32); letter-spacing: 0.18pt; vertical-align: baseline;\">organizational<\/span><span style=\"font-size: 10pt; font-family: &quot;Segoe UI&quot;; font-variant-numeric: normal; font-variant-east-asian: normal; font-variant-alternates: normal; font-variant-position: normal; color: rgb(35, 31, 32); letter-spacing: -1.12pt; vertical-align: baseline;\"> <\/span><span style=\"font-size: 10pt; font-family: &quot;Segoe UI&quot;; font-variant-numeric: normal; font-variant-east-asian: normal; font-variant-alternates: normal; font-variant-position: normal; color: rgb(35, 31, 32); letter-spacing: 0.24pt; vertical-align: baseline;\">outcome.<\/span><\/p>","approach_ar":"<p style=\"margin: 2.27pt 0in 0pt 0.01in; text-indent: 0in; line-height: normal; direction: ltr; unicode-bidi: embed; word-break: normal;\"><span style=\"font-size: 10pt; font-family: &quot;Segoe UI&quot;; font-variant-numeric: normal; font-variant-east-asian: normal; font-variant-alternates: normal; font-variant-position: normal; color: rgb(35, 31, 32); letter-spacing: 0.24pt; font-weight: bold; vertical-align: baseline;\">Employee<\/span><span style=\"font-size: 10pt; font-family: &quot;Segoe UI&quot;; font-variant-numeric: normal; font-variant-east-asian: normal; font-variant-alternates: normal; font-variant-position: normal; color: rgb(35, 31, 32); letter-spacing: -1.21pt; font-weight: bold; vertical-align: baseline;\">&nbsp;<\/span><span style=\"font-size: 10pt; font-family: &quot;Segoe UI&quot;; font-variant-numeric: normal; font-variant-east-asian: normal; font-variant-alternates: normal; font-variant-position: normal; color: rgb(35, 31, 32); letter-spacing: 0.21pt; font-weight: bold; vertical-align: baseline;\">Engagement:<\/span><\/p><p style=\"margin: 2.27pt 0in 0pt 0.01in; text-indent: 0in; line-height: normal; direction: ltr; unicode-bidi: embed; word-break: normal;\"><\/p><p><\/p><p style=\"margin: 0pt 0in 0pt 0.01in; text-indent: 0in; line-height: 19.2px; text-align: justify; direction: ltr; unicode-bidi: embed; word-break: normal;\"><span style=\"font-size: 10pt; font-family: &quot;Segoe UI&quot;; font-variant-numeric: normal; font-variant-east-asian: normal; font-variant-alternates: normal; font-variant-position: normal; color: rgb(35, 31, 32); letter-spacing: 0.03pt; vertical-align: baseline;\">The<\/span><span style=\"font-size: 10pt; font-family: &quot;Segoe UI&quot;; font-variant-numeric: normal; font-variant-east-asian: normal; font-variant-alternates: normal; font-variant-position: normal; color: rgb(35, 31, 32); letter-spacing: 0.06pt; vertical-align: baseline;\">&nbsp;<\/span><span style=\"font-size: 10pt; font-family: &quot;Segoe UI&quot;; font-variant-numeric: normal; font-variant-east-asian: normal; font-variant-alternates: normal; font-variant-position: normal; color: rgb(35, 31, 32); letter-spacing: 0.15pt; vertical-align: baseline;\">emotional,<\/span><span style=\"font-size: 10pt; font-family: &quot;Segoe UI&quot;; font-variant-numeric: normal; font-variant-east-asian: normal; font-variant-alternates: normal; font-variant-position: normal; color: rgb(35, 31, 32); letter-spacing: 0.09pt; vertical-align: baseline;\">&nbsp;<\/span><span style=\"font-size: 10pt; font-family: &quot;Segoe UI&quot;; font-variant-numeric: normal; font-variant-east-asian: normal; font-variant-alternates: normal; font-variant-position: normal; color: rgb(35, 31, 32); letter-spacing: 0.36pt; vertical-align: baseline;\">mental<\/span><span style=\"font-size: 10pt; font-family: &quot;Segoe UI&quot;; font-variant-numeric: normal; font-variant-east-asian: normal; font-variant-alternates: normal; font-variant-position: normal; color: rgb(35, 31, 32); letter-spacing: 0.36pt; vertical-align: baseline;\">,<\/span><span style=\"font-size: 10pt; font-family: &quot;Segoe UI&quot;; font-variant-numeric: normal; font-variant-east-asian: normal; font-variant-alternates: normal; font-variant-position: normal; color: rgb(35, 31, 32); letter-spacing: 0.09pt; vertical-align: baseline;\">&nbsp;<\/span><span style=\"font-size: 10pt; font-family: &quot;Segoe UI&quot;; font-variant-numeric: normal; font-variant-east-asian: normal; font-variant-alternates: normal; font-variant-position: normal; color: rgb(35, 31, 32); letter-spacing: 0.55pt; vertical-align: baseline;\">and<\/span><span style=\"font-size: 10pt; font-family: &quot;Segoe UI&quot;; font-variant-numeric: normal; font-variant-east-asian: normal; font-variant-alternates: normal; font-variant-position: normal; color: rgb(35, 31, 32); letter-spacing: 0.09pt; vertical-align: baseline;\">&nbsp;<\/span><span style=\"font-size: 10pt; font-family: &quot;Segoe UI&quot;; font-variant-numeric: normal; font-variant-east-asian: normal; font-variant-alternates: normal; font-variant-position: normal; color: rgb(35, 31, 32); letter-spacing: 0.27pt; vertical-align: baseline;\">physical<\/span><span style=\"font-size: 10pt; font-family: &quot;Segoe UI&quot;; font-variant-numeric: normal; font-variant-east-asian: normal; font-variant-alternates: normal; font-variant-position: normal; color: rgb(35, 31, 32); letter-spacing: 0.09pt; vertical-align: baseline;\">&nbsp;<\/span><span style=\"font-size: 10pt; font-family: &quot;Segoe UI&quot;; font-variant-numeric: normal; font-variant-east-asian: normal; font-variant-alternates: normal; font-variant-position: normal; color: rgb(35, 31, 32); letter-spacing: 0.27pt; vertical-align: baseline;\">connection<\/span><span style=\"font-size: 10pt; font-family: &quot;Segoe UI&quot;; font-variant-numeric: normal; font-variant-east-asian: normal; font-variant-alternates: normal; font-variant-position: normal; color: rgb(35, 31, 32); letter-spacing: 0.09pt; vertical-align: baseline;\">&nbsp;<\/span><span style=\"font-size: 10pt; font-family: &quot;Segoe UI&quot;; font-variant-numeric: normal; font-variant-east-asian: normal; font-variant-alternates: normal; font-variant-position: normal; color: rgb(35, 31, 32); letter-spacing: 0pt; vertical-align: baseline;\">of<\/span><span style=\"font-size: 10pt; font-family: &quot;Segoe UI&quot;; font-variant-numeric: normal; font-variant-east-asian: normal; font-variant-alternates: normal; font-variant-position: normal; color: rgb(35, 31, 32); letter-spacing: 0pt; vertical-align: baseline;\">&nbsp;<\/span><span style=\"font-size: 10pt; font-family: &quot;Segoe UI&quot;; font-variant-numeric: normal; font-variant-east-asian: normal; font-variant-alternates: normal; font-variant-position: normal; color: rgb(35, 31, 32); letter-spacing: 0.55pt; vertical-align: baseline;\">employees&nbsp;<\/span><span style=\"font-size: 10pt; font-family: &quot;Segoe UI&quot;; font-variant-numeric: normal; font-variant-east-asian: normal; font-variant-alternates: normal; font-variant-position: normal; color: rgb(35, 31, 32); letter-spacing: 0.21pt; vertical-align: baseline;\">to&nbsp;<\/span><span style=\"font-size: 10pt; font-family: &quot;Segoe UI&quot;; font-variant-numeric: normal; font-variant-east-asian: normal; font-variant-alternates: normal; font-variant-position: normal; color: rgb(35, 31, 32); letter-spacing: 0.36pt; vertical-align: baseline;\">the&nbsp;<\/span><span style=\"font-size: 10pt; font-family: &quot;Segoe UI&quot;; font-variant-numeric: normal; font-variant-east-asian: normal; font-variant-alternates: normal; font-variant-position: normal; color: rgb(35, 31, 32); letter-spacing: 0.33pt; vertical-align: baseline;\">organization&nbsp;<\/span><span style=\"font-size: 10pt; font-family: &quot;Segoe UI&quot;; font-variant-numeric: normal; font-variant-east-asian: normal; font-variant-alternates: normal; font-variant-position: normal; color: rgb(35, 31, 32); letter-spacing: 0.42pt; vertical-align: baseline;\">that&nbsp;<\/span><span style=\"font-size: 10pt; font-family: &quot;Segoe UI&quot;; color: rgb(35, 31, 32); letter-spacing: 0.33pt;\">stimulates<\/span><span style=\"font-size: 10pt; font-family: &quot;Segoe UI&quot;; font-variant-numeric: normal; font-variant-east-asian: normal; font-variant-alternates: normal; font-variant-position: normal; color: rgb(35, 31, 32); letter-spacing: 0.33pt; vertical-align: baseline;\">&nbsp;<\/span><span style=\"font-size: 10pt; font-family: &quot;Segoe UI&quot;; font-variant-numeric: normal; font-variant-east-asian: normal; font-variant-alternates: normal; font-variant-position: normal; color: rgb(35, 31, 32); letter-spacing: 0.69pt; vertical-align: baseline;\">an<\/span><span style=\"font-size: 10pt; font-family: &quot;Segoe UI&quot;; font-variant-numeric: normal; font-variant-east-asian: normal; font-variant-alternates: normal; font-variant-position: normal; color: rgb(35, 31, 32); letter-spacing: 0.69pt; vertical-align: baseline;\">&nbsp;<\/span><span style=\"font-size: 10pt; font-family: &quot;Segoe UI&quot;; font-variant-numeric: normal; font-variant-east-asian: normal; font-variant-alternates: normal; font-variant-position: normal; color: rgb(35, 31, 32); letter-spacing: 0.15pt; vertical-align: baseline;\">extraordinary<\/span><span style=\"font-size: 10pt; font-family: &quot;Segoe UI&quot;; font-variant-numeric: normal; font-variant-east-asian: normal; font-variant-alternates: normal; font-variant-position: normal; color: rgb(35, 31, 32); letter-spacing: -0.88pt; vertical-align: baseline;\">&nbsp;<\/span><span style=\"font-size: 10pt; font-family: &quot;Segoe UI&quot;; font-variant-numeric: normal; font-variant-east-asian: normal; font-variant-alternates: normal; font-variant-position: normal; color: rgb(35, 31, 32); letter-spacing: 0.12pt; vertical-align: baseline;\">contribution<\/span><span style=\"font-size: 10pt; font-family: &quot;Segoe UI&quot;; font-variant-numeric: normal; font-variant-east-asian: normal; font-variant-alternates: normal; font-variant-position: normal; color: rgb(35, 31, 32); letter-spacing: -0.88pt; vertical-align: baseline;\">&nbsp;<\/span><span style=\"font-size: 10pt; font-family: &quot;Segoe UI&quot;; font-variant-numeric: normal; font-variant-east-asian: normal; font-variant-alternates: normal; font-variant-position: normal; color: rgb(35, 31, 32); letter-spacing: 0.27pt; vertical-align: baseline;\">that<\/span><span style=\"font-size: 10pt; font-family: &quot;Segoe UI&quot;; font-variant-numeric: normal; font-variant-east-asian: normal; font-variant-alternates: normal; font-variant-position: normal; color: rgb(35, 31, 32); letter-spacing: -0.88pt; vertical-align: baseline;\">&nbsp;<\/span><span style=\"font-size: 10pt; font-family: &quot;Segoe UI&quot;; font-variant-numeric: normal; font-variant-east-asian: normal; font-variant-alternates: normal; font-variant-position: normal; color: rgb(35, 31, 32); letter-spacing: 0.39pt; vertical-align: baseline;\">achieves<\/span><span style=\"font-size: 10pt; font-family: &quot;Segoe UI&quot;; font-variant-numeric: normal; font-variant-east-asian: normal; font-variant-alternates: normal; font-variant-position: normal; color: rgb(35, 31, 32); letter-spacing: -0.88pt; vertical-align: baseline;\">&nbsp;<\/span><span style=\"font-size: 10pt; font-family: &quot;Segoe UI&quot;; font-variant-numeric: normal; font-variant-east-asian: normal; font-variant-alternates: normal; font-variant-position: normal; color: rgb(35, 31, 32); letter-spacing: 0.97pt; vertical-align: baseline;\">a<\/span><span style=\"font-size: 10pt; font-family: &quot;Segoe UI&quot;; font-variant-numeric: normal; font-variant-east-asian: normal; font-variant-alternates: normal; font-variant-position: normal; color: rgb(35, 31, 32); letter-spacing: 0.97pt; vertical-align: baseline;\">&nbsp;<\/span><span style=\"font-size: 10pt; font-family: &quot;Segoe UI&quot;; font-variant-numeric: normal; font-variant-east-asian: normal; font-variant-alternates: normal; font-variant-position: normal; color: rgb(35, 31, 32); letter-spacing: 0.09pt; vertical-align: baseline;\">win-win<\/span><span style=\"font-size: 10pt; font-family: &quot;Segoe UI&quot;; font-variant-numeric: normal; font-variant-east-asian: normal; font-variant-alternates: normal; font-variant-position: normal; color: rgb(35, 31, 32); letter-spacing: -0.12pt; vertical-align: baseline;\">&nbsp;<\/span><span style=\"font-size: 10pt; font-family: &quot;Segoe UI&quot;; font-variant-numeric: normal; font-variant-east-asian: normal; font-variant-alternates: normal; font-variant-position: normal; color: rgb(35, 31, 32); letter-spacing: 0.12pt; vertical-align: baseline;\">situation<\/span><span style=\"font-size: 10pt; font-family: &quot;Segoe UI&quot;; font-variant-numeric: normal; font-variant-east-asian: normal; font-variant-alternates: normal; font-variant-position: normal; color: rgb(35, 31, 32); letter-spacing: -0.12pt; vertical-align: baseline;\">;<\/span><span style=\"font-size: 10pt; font-family: &quot;Segoe UI&quot;; font-variant-numeric: normal; font-variant-east-asian: normal; font-variant-alternates: normal; font-variant-position: normal; color: rgb(35, 31, 32); letter-spacing: -0.09pt; vertical-align: baseline;\">&nbsp;<\/span><span style=\"font-size: 10pt; font-family: &quot;Segoe UI&quot;; font-variant-numeric: normal; font-variant-east-asian: normal; font-variant-alternates: normal; font-variant-position: normal; color: rgb(35, 31, 32); letter-spacing: 0.18pt; vertical-align: baseline;\">better<\/span><span style=\"font-size: 10pt; font-family: &quot;Segoe UI&quot;; font-variant-numeric: normal; font-variant-east-asian: normal; font-variant-alternates: normal; font-variant-position: normal; color: rgb(35, 31, 32); letter-spacing: -0.09pt; vertical-align: baseline;\">&nbsp;<\/span><span style=\"font-size: 10pt; font-family: &quot;Segoe UI&quot;; font-variant-numeric: normal; font-variant-east-asian: normal; font-variant-alternates: normal; font-variant-position: normal; color: rgb(35, 31, 32); letter-spacing: 0.39pt; vertical-align: baseline;\">employee<\/span><span style=\"font-size: 10pt; font-family: &quot;Segoe UI&quot;; font-variant-numeric: normal; font-variant-east-asian: normal; font-variant-alternates: normal; font-variant-position: normal; color: rgb(35, 31, 32); letter-spacing: -0.12pt; vertical-align: baseline;\">&nbsp;<\/span><span style=\"font-size: 10pt; font-family: &quot;Segoe UI&quot;; font-variant-numeric: normal; font-variant-east-asian: normal; font-variant-alternates: normal; font-variant-position: normal; color: rgb(35, 31, 32); letter-spacing: 0.3pt; vertical-align: baseline;\">experience&nbsp;<\/span><span style=\"font-size: 10pt; font-family: &quot;Segoe UI&quot;; font-variant-numeric: normal; font-variant-east-asian: normal; font-variant-alternates: normal; font-variant-position: normal; color: rgb(35, 31, 32); letter-spacing: 0.55pt; vertical-align: baseline;\">and<\/span><span style=\"font-size: 10pt; font-family: &quot;Segoe UI&quot;; font-variant-numeric: normal; font-variant-east-asian: normal; font-variant-alternates: normal; font-variant-position: normal; color: rgb(35, 31, 32); letter-spacing: 0.55pt; vertical-align: baseline;\">&nbsp;better<\/span><span style=\"font-size: 10pt; font-family: &quot;Segoe UI&quot;; font-variant-numeric: normal; font-variant-east-asian: normal; font-variant-alternates: normal; font-variant-position: normal; color: rgb(35, 31, 32); letter-spacing: -1.12pt; vertical-align: baseline;\">&nbsp;<\/span><span style=\"font-size: 10pt; font-family: &quot;Segoe UI&quot;; font-variant-numeric: normal; font-variant-east-asian: normal; font-variant-alternates: normal; font-variant-position: normal; color: rgb(35, 31, 32); letter-spacing: 0.18pt; vertical-align: baseline;\">organizational<\/span><span style=\"font-size: 10pt; font-family: &quot;Segoe UI&quot;; font-variant-numeric: normal; font-variant-east-asian: normal; font-variant-alternates: normal; font-variant-position: normal; color: rgb(35, 31, 32); letter-spacing: -1.12pt; vertical-align: baseline;\">&nbsp;<\/span><span style=\"font-size: 10pt; font-family: &quot;Segoe UI&quot;; font-variant-numeric: normal; font-variant-east-asian: normal; font-variant-alternates: normal; font-variant-position: normal; color: rgb(35, 31, 32); letter-spacing: 0.24pt; vertical-align: baseline;\">outcome.<\/span><\/p>","icon":"1720073296.jpg","is_active":0,"deleted_at":null,"created_at":"2024-07-04 10:08:16","updated_at":"2024-07-04 10:08:16"},{"id":7,"service":2,"approach":"<p><span style=\"font-family: Cairo, sans-serif; font-size: 14.4px; text-align: center;\">We also believe in the value of enhancing the employee experience and thus we also capture employees\u2019 voices.<\/span><br><\/p>","approach_ar":"<p><span style=\"font-family: Cairo, sans-serif; font-size: 14.4px; text-align: center;\">We also believe in the value of enhancing the employee experience and thus we also capture employees\u2019 voices.<\/span><br><\/p>","icon":"1720080805.jpg","is_active":0,"deleted_at":null,"created_at":"2024-07-04 12:13:25","updated_at":"2024-07-04 12:13:25"},{"id":8,"service":2,"approach":"<p><span style=\"font-family: Cairo, sans-serif; font-size: 14.4px; text-align: center;\">We don't believe in a one-size-fits-all approach and in \"Best Practices\" and thus we assess the outcome\/results and identify the possible root causes which need to be validated &amp;refined.<\/span><br><\/p>","approach_ar":"<p><span style=\"font-family: Cairo, sans-serif; font-size: 14.4px; text-align: center;\">We don't believe in a one-size-fits-all approach and in \"Best Practices\" and thus we assess the outcome\/results and identify the possible root causes which need to be validated &amp;refined.<\/span><br><\/p>","icon":"1720080891.webp","is_active":0,"deleted_at":null,"created_at":"2024-07-04 12:14:51","updated_at":"2024-07-04 12:14:51"},{"id":9,"service":3,"approach":"4Ps stands for People, Performance, Plasticity and Presence","approach_ar":"<p>4Ps stands for People, Performance, Plasticity and Presence<br><\/p>","icon":"1720085151.png","is_active":0,"deleted_at":null,"created_at":"2024-07-04 13:25:51","updated_at":"2024-07-04 13:25:51"}]